scuapi/__init__.py
scuapi/scuapi.py
streamingcommunity_unofficialapi-4.0.1.dist-info/licenses/LICENSE
streamingcommunity_unofficialapi-4.0.1.dist-info/METADATA
streamingcommunity_unofficialapi-4.0.1.dist-info/WHEEL
streamingcommunity_unofficialapi-4.0.1.dist-info/top_level.txt
streamingcommunity_unofficialapi-4.0.1.dist-info/RECORD
