Metadata-Version: 2.4
Name: streamingcommunity-unofficialapi
Version: 4.0.1
Summary: A simple unofficial api for the italian StreamingCommunity website.
Home-page: https://github.com/Blu-Tiger/streamingcommunity-unofficialapi
Author: BluTiger
License: MIT
Classifier: Programming Language :: Python :: 3
Classifier: License :: OSI Approved :: MIT License
Classifier: Operating System :: OS Independent
Classifier: Topic :: Utilities
Requires-Python: >= 3.10
License-File: LICENSE
Requires-Dist: requests
Dynamic: author
Dynamic: classifier
Dynamic: description
Dynamic: description-content-type
Dynamic: home-page
Dynamic: license
Dynamic: license-file
Dynamic: requires-dist
Dynamic: requires-python
Dynamic: summary
